chipys_5e_companion/__about__.py
chipys_5e_companion/__init__.py
chipys_5e_companion/dice.py
chipys_5e_companion/main.py
chipys_5e_companion/QT/gui.py
chipys_5e_companion/QT/gui.ui
chipys_5e_companion-0.0.5.dist-info/METADATA
chipys_5e_companion-0.0.5.dist-info/WHEEL
chipys_5e_companion-0.0.5.dist-info/licenses/LICENSE.txt
chipys_5e_companion-0.0.5.dist-info/RECORD
